ispprogrammer/IODevices.py
ispprogrammer/ISPConnection.py
ispprogrammer/__init__.py
ispprogrammer/cli.py
ispprogrammer/gui.py
ispprogrammer/lpctools_parts.def
ispprogrammer/parts_definitions.py
ispprogrammer/tools.py
ispprogrammer-1.3.0.dist-info/licenses/LICENSE
ispprogrammer-1.3.0.dist-info/METADATA
ispprogrammer-1.3.0.dist-info/WHEEL
ispprogrammer-1.3.0.dist-info/entry_points.txt
ispprogrammer-1.3.0.dist-info/top_level.txt
ispprogrammer-1.3.0.dist-info/RECORD
