Metadata-Version: 2.4
Name: ispprogrammer
Version: 1.3.0
Summary: NXP ISP Cortex-M programming tool
Author-email: Simon Hobbs <simon.hobbs@electrooptical.net>
License: MIT License
Project-URL: repository, https://github.com/snhobbs/isp-programmer
Project-URL: url, https://github.com/snhobbs/isp-programmer
Keywords: isp,nxp,program,uart
Classifier: Programming Language :: Python :: 3
Requires-Python: >=3.9
License-File: LICENSE
Requires-Dist: pyserial>=3.3
Requires-Dist: intelhex>=2.3.0
Requires-Dist: pycrc>=0.10.0
Requires-Dist: click>=8.0.0
Dynamic: license-file
